datamart_materialize/__init__.py
datamart_materialize/common.py
datamart_materialize/d3m.py
datamart_materialize/detect.py
datamart_materialize/excel.py
datamart_materialize/excel97.py
datamart_materialize/noaa.py
datamart_materialize/parquet.py
datamart_materialize/pivot.py
datamart_materialize/spss.py
datamart_materialize/stata.py
datamart_materialize/tsv.py
datamart_materialize/types.py
datamart_materialize/utils.py
datamart_materialize-0.11.dist-info/LICENSE.txt
datamart_materialize-0.11.dist-info/METADATA
datamart_materialize-0.11.dist-info/NOTICE.txt
datamart_materialize-0.11.dist-info/WHEEL
datamart_materialize-0.11.dist-info/entry_points.txt
datamart_materialize-0.11.dist-info/top_level.txt
datamart_materialize-0.11.dist-info/RECORD
